pyChainedProxy/__init__.py
pyChainedProxy/__main__.py
pyChainedProxy-1.2.dist-info/LICENSE
pyChainedProxy-1.2.dist-info/METADATA
pyChainedProxy-1.2.dist-info/WHEEL
pyChainedProxy-1.2.dist-info/entry_points.txt
pyChainedProxy-1.2.dist-info/top_level.txt
pyChainedProxy-1.2.dist-info/RECORD
