Metadata-Version: 2.1
Name: pyChainedProxy
Version: 1.2
Summary: A python module for Chaining of Proxies.
Home-page: https://github.com/nighthawkk/pyChainedProxy
Author: Aman Kumar
Author-email: akdapunk@gmail.com
License: UNKNOWN
Platform: UNKNOWN
Classifier: Programming Language :: Python :: 3.8
Classifier: License :: OSI Approved :: MIT License
Classifier: Operating System :: OS Independent
